helpdsf/__init__.py
helpdsf/helpmla.py
HelpMLA-0.1.dist-info/LICENSE
HelpMLA-0.1.dist-info/METADATA
HelpMLA-0.1.dist-info/WHEEL
HelpMLA-0.1.dist-info/top_level.txt
HelpMLA-0.1.dist-info/RECORD
