Metadata-Version: 2.1
Name: HelpMLA
Version: 0.1
Summary: Библиотека с четырьмя методами, возвращающими 1, 2, 3 и 4.
Home-page: https://github.com/ваш_репозиторий/HelpDSF
Author: Ваше Имя
Author-email: ваш.email@example.com
Classifier: Programming Language :: Python :: 3
Classifier: License :: OSI Approved :: MIT License
Classifier: Operating System :: OS Independent
Requires-Python: >=3.6
License-File: LICENSE
